<annotation>
    <folder>images</folder>
    <filename>1cff12ff-be70-4195-b298-27b019ea9cdb.jpg</filename>
    <size>
        <width>640</width>
        <height>360</height>
        <depth>3</depth>
    </size>
    <segmented>0</segmented>
    <object>
        <name>wand</name>
        <pose>Unspecified</pose>
        <truncated>0</truncated>
        <occluded>0</occluded>
        <difficult>0</difficult>
        <bndbox>
            <xmin>538</xmin>
            <ymin>157</ymin>
            <xmax>589</xmax>
            <ymax>205</ymax>
        </bndbox>
    </object>
</annotation>