<annotation>
    <folder>images</folder>
    <filename>c023e92c-7741-4427-b300-33efb99b96d6.jpg</filename>
    <size>
        <width>640</width>
        <height>360</height>
        <depth>3</depth>
    </size>
    <segmented>0</segmented>
    <object>
        <name>wand</name>
        <pose>Unspecified</pose>
        <truncated>0</truncated>
        <occluded>0</occluded>
        <difficult>0</difficult>
        <bndbox>
            <xmin>142</xmin>
            <ymin>105</ymin>
            <xmax>178</xmax>
            <ymax>141</ymax>
        </bndbox>
    </object>
    <object>
        <name>wand</name>
        <pose>Unspecified</pose>
        <truncated>0</truncated>
        <occluded>0</occluded>
        <difficult>0</difficult>
        <bndbox>
            <xmin>323</xmin>
            <ymin>135</ymin>
            <xmax>355</xmax>
            <ymax>164</ymax>
        </bndbox>
    </object>
</annotation>